simple_media_manager/__init__.py
simple_media_manager/admin.py
simple_media_manager/apps.py
simple_media_manager/domain/__init__.py
simple_media_manager/domain/command/__init__.py
simple_media_manager/domain/command/image.py
simple_media_manager/domain/command/video.py
simple_media_manager/domain/entities/__init__.py
simple_media_manager/domain/entities/constants.py
simple_media_manager/domain/entities/enums.py
simple_media_manager/domain/repository/__init__.py
simple_media_manager/domain/repository/image.py
simple_media_manager/domain/repository/video.py
simple_media_manager/infrastructure/__init__.py
simple_media_manager/infrastructure/adapters/__init__.py
simple_media_manager/infrastructure/adapters/image.py
simple_media_manager/infrastructure/adapters/video.py
simple_media_manager/infrastructure/common/__init__.py
simple_media_manager/infrastructure/common/class_responses/__init__.py
simple_media_manager/infrastructure/common/class_responses/error_response.py
simple_media_manager/infrastructure/common/data_responses/__init__.py
simple_media_manager/infrastructure/common/data_responses/data_response.py
simple_media_manager/infrastructure/common/exception_handlers.py
simple_media_manager/infrastructure/common/pagination.py
simple_media_manager/infrastructure/common/serializers/__init__.py
simple_media_manager/infrastructure/common/serializers/common_serializer.py
simple_media_manager/infrastructure/common/serializers/custom_fields/__init__.py
simple_media_manager/infrastructure/common/serializers/custom_fields/fields.py
simple_media_manager/infrastructure/dependency/__init__.py
simple_media_manager/infrastructure/dependency/registry.py
simple_media_manager/infrastructure/migrations/0001_initial.py
simple_media_manager/infrastructure/migrations/0002_image_compact_image_thumbnail_alter_image_image.py
simple_media_manager/infrastructure/migrations/0003_alter_image_options_rename_image_image_original.py
simple_media_manager-0.2.3.dist-info/METADATA
simple_media_manager-0.2.3.dist-info/WHEEL
simple_media_manager-0.2.3.dist-info/RECORD
