Metadata-Version: 2.1
Name: simple-media-manager
Version: 0.2.3
Summary: 
License: MIT
Author: aliseylaneh
Author-email: aliseylaneh@gmail.com
Requires-Python: >=3.11,<4.0
Classifier: License :: OSI Approved :: MIT License
Classifier: Programming Language :: Python :: 3
Classifier: Programming Language :: Python :: 3.11
Classifier: Programming Language :: Python :: 3.12
Requires-Dist: django (>=4.0.7)
Requires-Dist: djangorestframework (>=3.13.1)
Requires-Dist: djangorestframework-camel-case (>=1.4.2)
Requires-Dist: djangorestframework-simplejwt (>=5.2.2)
Requires-Dist: drf-spectacular (>=0.24.2)
Requires-Dist: ffmpeg-python (>=0.2.0,<0.3.0)
Requires-Dist: pillow (>=10.2.0)
Requires-Dist: psycopg2-binary (>=2.9.1)
